translation_comparator/__init__.py
translation_comparator/comparison_helpers.py
translation_comparator/pair_finders.py
translation_comparator/path_helpers.py
translation_comparator/show_functions.py
translation_comparator/typedefs.py
translation_comparator/utils.py
translation_comparator/cython/__init__.py
translation_comparator/cython/annotated_html_parser.py
translation_comparator/cython/code_comparator.py
translation_comparator/cython/path_builders.py
translation_comparator/cython/settings.py
translation_comparator/cython/with_cython.py
translation_comparator-0.1.0.dist-info/LICENSE
translation_comparator-0.1.0.dist-info/METADATA
translation_comparator-0.1.0.dist-info/WHEEL
translation_comparator-0.1.0.dist-info/top_level.txt
translation_comparator-0.1.0.dist-info/RECORD
