Metadata-Version: 2.1
Name: translation-comparator
Version: 0.1.0
Summary: Helps to compare translated code.
Home-page: https://github.com/0dminnimda/translation_comparator
Author: 0dminnimda
Author-email: 0dminnimda.contact@gmail.com
License: MIT
Project-URL: Bug tracker, https://github.com/0dminnimda/translation_comparator/issues
Platform: UNKNOWN
Classifier: Development Status :: 3 - Alpha
Classifier: Intended Audience :: Developers
Classifier: License :: OSI Approved :: MIT License
Classifier: Programming Language :: Python :: 3.7
Classifier: Programming Language :: Python :: 3.8
Classifier: Programming Language :: Python :: 3.9
Classifier: Topic :: Software Development :: Libraries :: Python Modules
Classifier: Topic :: Utilities
Classifier: Typing :: Typed
Requires-Python: >=3.7
License-File: LICENSE
Provides-Extra: cython
Requires-Dist: beautifulsoup4 (>=4.7.0) ; extra == 'cython'
Requires-Dist: cython (>=0.22) ; extra == 'cython'
